vaapi/__init__.py
vaapi/vaapi.py
BU_VAT-0.1.1.dist-info/METADATA
BU_VAT-0.1.1.dist-info/WHEEL
BU_VAT-0.1.1.dist-info/top_level.txt
BU_VAT-0.1.1.dist-info/RECORD
